{
  "audiocall": {
    "ruName": "Аудиовызов",
    "rules": [
      "Эта игра предназначена для тренировки слухового восприятия речи.",
      "Для управления помимо мыши Вы можете использовать клавиатуру:",
      "- 'Ввод' - пропуск слова или переход к следующему вопросу;",
      "- 'Пробел' - повтор аудиозаписи слова;",
      "- 'Клавиши с цифрами' - выбор варианта ответа.",
      "Удачи!"
    ]
  },
  "sprint": {
    "ruName": "Cпринт",
    "rules": [
      "Эта игра предназначена для повторения изученных слов.",
      "Для управления помимо мыши Вы можете использовать клавиатуру:",
      "- 'Стрелка влево' - выбор опции 'Неверно';",
      "- 'Стрелка вправо' - выбор опции 'Верно'.",
      "Удачи!"
    ]
  }
}
